kube_watch/__init__.py
kube_watch/enums/__init__.py
kube_watch/enums/kube.py
kube_watch/enums/logic.py
kube_watch/enums/providers.py
kube_watch/enums/workflow.py
kube_watch/models/__init__.py
kube_watch/models/common.py
kube_watch/models/workflow.py
kube_watch/modules/__init__.py
kube_watch/modules/clusters/__init__.py
kube_watch/modules/clusters/kube.py
kube_watch/modules/database/__init__.py
kube_watch/modules/database/model.py
kube_watch/modules/database/postgre.py
kube_watch/modules/logic/actions.py
kube_watch/modules/logic/checks.py
kube_watch/modules/logic/load.py
kube_watch/modules/logic/merge.py
kube_watch/modules/logic/scheduler.py
kube_watch/modules/logic/trasnform.py
kube_watch/modules/mock/__init__.py
kube_watch/modules/mock/mock_generator.py
kube_watch/modules/providers/__init__.py
kube_watch/modules/providers/aws.py
kube_watch/modules/providers/git.py
kube_watch/modules/providers/github.py
kube_watch/modules/providers/vault.py
kube_watch/standalone/metarecogen/ckan_to_gn.py
kube_watch/watch/__init__.py
kube_watch/watch/helpers.py
kube_watch/watch/workflow.py
kubernetes_watch-0.1.12.dist-info/LICENSE
kubernetes_watch-0.1.12.dist-info/METADATA
kubernetes_watch-0.1.12.dist-info/WHEEL
kubernetes_watch-0.1.12.dist-info/RECORD
