Metadata-Version: 2.1
Name: kubernetes-watch
Version: 0.1.12
Summary: 
Author: bmotevalli
Author-email: b.motevalli@gmail.com
Requires-Python: >=3.10,<3.14
Classifier: Programming Language :: Python :: 3
Classifier: Programming Language :: Python :: 3.10
Classifier: Programming Language :: Python :: 3.11
Classifier: Programming Language :: Python :: 3.12
Requires-Dist: GitPython (>=3.1.43,<4.0.0)
Requires-Dist: PyYAML (>=6.0.1,<7.0.0)
Requires-Dist: boto3 (>=1.34.68,<2.0.0)
Requires-Dist: humps (>=0.2.2,<0.3.0)
Requires-Dist: hvac (>=2.1.0,<3.0.0)
Requires-Dist: kubernetes (>=29.0.0,<30.0.0)
Requires-Dist: prefect (==3.4.18)
Requires-Dist: psycopg2 (>=2.9.10,<3.0.0)
Requires-Dist: pydantic (>=2.11.7,<3.0.0)
Requires-Dist: requests (>=2.32.3,<3.0.0)
